MANIFEST.in
README.md
requirements-dev.txt
requirements-pre-commit.txt
requirements-tests.txt
requirements.txt
setup.cfg
setup.py
hassio_repo_updater.egg-info/PKG-INFO
hassio_repo_updater.egg-info/SOURCES.txt
hassio_repo_updater.egg-info/dependency_links.txt
hassio_repo_updater.egg-info/entry_points.txt
hassio_repo_updater.egg-info/requires.txt
hassio_repo_updater.egg-info/top_level.txt
repositoryupdater/__init__.py
repositoryupdater/__main__.py
repositoryupdater/addon.py
repositoryupdater/cli.py
repositoryupdater/const.py
repositoryupdater/dockerhub.py
repositoryupdater/github.py
repositoryupdater/repository.py
script/__init__.py
script/version_bump.py
tests/__init__.py
tests/test_dockerhub.py