Metadata-Version: 2.1
Name: hassio-repo-updater
Version: 0.5.2
Summary: UNKNOWN
Home-page: https://github.com/Limych/repository-updater
Author: Andrey Khrolenok
Author-email: andrey@khrolenok.ru
License: MIT
Download-URL: https://github.com/Limych/repository-updater/archive/0.5.2.tar.gz
Keywords: hassio,hass.io,addons,repository,home assistant,home-assistant,add-ons,limych
Platform: any
Classifier: Environment :: Console
Classifier: Intended Audience :: Developers
Classifier: License :: OSI Approved :: MIT License
Classifier: Programming Language :: Python
Classifier: Programming Language :: Python :: 3
Classifier: Programming Language :: Python :: 3 :: Only
Classifier: Topic :: Software Development :: Build Tools
Classifier: Topic :: Utilities
